gitee/__init__.py
gitee/api_client.py
gitee/configuration.py
gitee/rest.py
gitee/api/__init__.py
gitee/api/activity_api.py
gitee/api/emails_api.py
gitee/api/enterprises_api.py
gitee/api/gists_api.py
gitee/api/git_data_api.py
gitee/api/issues_api.py
gitee/api/labels_api.py
gitee/api/milestones_api.py
gitee/api/miscellaneous_api.py
gitee/api/organizations_api.py
gitee/api/pull_requests_api.py
gitee/api/repositories_api.py
gitee/api/search_api.py
gitee/api/users_api.py
gitee/api/webhooks_api.py
gitee/models/__init__.py
gitee/models/blob.py
gitee/models/body.py
gitee/models/body1.py
gitee/models/body10.py
gitee/models/body11.py
gitee/models/body12.py
gitee/models/body13.py
gitee/models/body14.py
gitee/models/body15.py
gitee/models/body16.py
gitee/models/body17.py
gitee/models/body18.py
gitee/models/body19.py
gitee/models/body2.py
gitee/models/body20.py
gitee/models/body21.py
gitee/models/body22.py
gitee/models/body23.py
gitee/models/body24.py
gitee/models/body25.py
gitee/models/body26.py
gitee/models/body27.py
gitee/models/body28.py
gitee/models/body29.py
gitee/models/body3.py
gitee/models/body30.py
gitee/models/body31.py
gitee/models/body32.py
gitee/models/body33.py
gitee/models/body34.py
gitee/models/body35.py
gitee/models/body36.py
gitee/models/body37.py
gitee/models/body38.py
gitee/models/body39.py
gitee/models/body4.py
gitee/models/body40.py
gitee/models/body41.py
gitee/models/body42.py
gitee/models/body43.py
gitee/models/body44.py
gitee/models/body45.py
gitee/models/body46.py
gitee/models/body47.py
gitee/models/body48.py
gitee/models/body49.py
gitee/models/body5.py
gitee/models/body50.py
gitee/models/body51.py
gitee/models/body52.py
gitee/models/body53.py
gitee/models/body54.py
gitee/models/body55.py
gitee/models/body56.py
gitee/models/body57.py
gitee/models/body58.py
gitee/models/body59.py
gitee/models/body6.py
gitee/models/body60.py
gitee/models/body61.py
gitee/models/body62.py
gitee/models/body63.py
gitee/models/body64.py
gitee/models/body65.py
pygitee-1.0.1.dist-info/LICENSE
pygitee-1.0.1.dist-info/METADATA
pygitee-1.0.1.dist-info/WHEEL
pygitee-1.0.1.dist-info/top_level.txt
pygitee-1.0.1.dist-info/zip-safe
pygitee-1.0.1.dist-info/RECORD
