Metadata-Version: 2.1
Name: pygitee
Version: 1.0.1
Summary: 码云 Open API
Home-page: https://gitee.com/kingreatwill/pygitee
Author-email: 
License: UNKNOWN
Keywords: Swagger,码云 Open API
Platform: UNKNOWN
Requires-Dist: urllib3 (>=1.15)
Requires-Dist: six (>=1.10)
Requires-Dist: certifi
Requires-Dist: python-dateutil
